{"metadata": {"dbt_schema_version": "https://schemas.getdbt.com/dbt/run-results/v6.json", "dbt_version": "1.8.8", "generated_at": "2025-10-15T03:53:20.392442Z", "invocation_id": "574e2f7e-7081-44de-961a-e68dd822cd38", "env": {}}, "results": [{"status": "pass", "timing": [{"name": "compile", "started_at": "2025-10-15T03:53:19.694812Z", "completed_at": "2025-10-15T03:53:19.727628Z"}, {"name": "execute", "started_at": "2025-10-15T03:53:19.729642Z", "completed_at": "2025-10-15T03:53:19.817760Z"}], "thread_id": "Thread-2 (worker)", "execution_time": 0.1558089256286621, "adapter_response": {"_message": "SELECT 1", "code": "SELECT", "rows_affected": 1}, "message": null, "failures": 0, "unique_id": "test.its_on_sale.not_null_fact_price_history_ts_utc.78d3e6c462", "compiled": true, "compiled_code": "\n    \n    \n\n\n\nselect ts_utc\nfrom \"neondb\".\"public_marts\".\"fact_price_history\"\nwhere ts_utc is null\n\n\n", "relation_name": null}, {"status": "pass", "timing": [{"name": "compile", "started_at": "2025-10-15T03:53:19.704423Z", "completed_at": "2025-10-15T03:53:19.728636Z"}, {"name": "execute", "started_at": "2025-10-15T03:53:19.736251Z", "completed_at": "2025-10-15T03:53:19.820928Z"}], "thread_id": "Thread-4 (worker)", "execution_time": 0.16457295417785645, "adapter_response": {"_message": "SELECT 1", "code": "SELECT", "rows_affected": 1}, "message": null, "failures": 0, "unique_id": "test.its_on_sale.not_null_price_events_event_type.61d7de2d7b", "compiled": true, "compiled_code": "\n    \n    \n\n\n\nselect event_type\nfrom \"neondb\".\"public_marts\".\"price_events\"\nwhere event_type is null\n\n\n", "relation_name": null}, {"status": "pass", "timing": [{"name": "compile", "started_at": "2025-10-15T03:53:19.674403Z", "completed_at": "2025-10-15T03:53:19.709523Z"}, {"name": "execute", "started_at": "2025-10-15T03:53:19.710528Z", "completed_at": "2025-10-15T03:53:19.823625Z"}], "thread_id": "Thread-1 (worker)", "execution_time": 0.1701068878173828, "adapter_response": {"_message": "SELECT 1", "code": "SELECT", "rows_affected": 1}, "message": null, "failures": 0, "unique_id": "test.its_on_sale.not_null_fact_price_history_id.110f7c1113", "compiled": true, "compiled_code": "\n    \n    \n\n\n\nselect id\nfrom \"neondb\".\"public_marts\".\"fact_price_history\"\nwhere id is null\n\n\n", "relation_name": null}, {"status": "pass", "timing": [{"name": "compile", "started_at": "2025-10-15T03:53:19.699884Z", "completed_at": "2025-10-15T03:53:19.727628Z"}, {"name": "execute", "started_at": "2025-10-15T03:53:19.732658Z", "completed_at": "2025-10-15T03:53:19.822121Z"}], "thread_id": "Thread-3 (worker)", "execution_time": 0.16775846481323242, "adapter_response": {"_message": "SELECT 1", "code": "SELECT", "rows_affected": 1}, "message": null, "failures": 0, "unique_id": "test.its_on_sale.not_null_latest_price_per_product_product_id.48bbe621b2", "compiled": true, "compiled_code": "\n    \n    \n\n\n\nselect product_id\nfrom \"neondb\".\"public_marts\".\"latest_price_per_product\"\nwhere product_id is null\n\n\n", "relation_name": null}, {"status": "pass", "timing": [{"name": "compile", "started_at": "2025-10-15T03:53:19.829728Z", "completed_at": "2025-10-15T03:53:19.837451Z"}, {"name": "execute", "started_at": "2025-10-15T03:53:19.839945Z", "completed_at": "2025-10-15T03:53:19.931834Z"}], "thread_id": "Thread-2 (worker)", "execution_time": 0.10931134223937988, "adapter_response": {"_message": "SELECT 1", "code": "SELECT", "rows_affected": 1}, "message": null, "failures": 0, "unique_id": "test.its_on_sale.not_null_price_events_product_id.d5bcb90d02", "compiled": true, "compiled_code": "\n    \n    \n\n\n\nselect product_id\nfrom \"neondb\".\"public_marts\".\"price_events\"\nwhere product_id is null\n\n\n", "relation_name": null}, {"status": "pass", "timing": [{"name": "compile", "started_at": "2025-10-15T03:53:19.868873Z", "completed_at": "2025-10-15T03:53:19.878656Z"}, {"name": "execute", "started_at": "2025-10-15T03:53:19.883728Z", "completed_at": "2025-10-15T03:53:19.954910Z"}], "thread_id": "Thread-3 (worker)", "execution_time": 0.10785722732543945, "adapter_response": {"_message": "SELECT 1", "code": "SELECT", "rows_affected": 1}, "message": null, "failures": 0, "unique_id": "test.its_on_sale.not_null_stg_price_history_product_id.082361509e", "compiled": true, "compiled_code": "\n    \n    \n\n\n\nselect product_id\nfrom \"neondb\".\"public_staging\".\"stg_price_history\"\nwhere product_id is null\n\n\n", "relation_name": null}, {"status": "pass", "timing": [{"name": "compile", "started_at": "2025-10-15T03:53:19.858728Z", "completed_at": "2025-10-15T03:53:19.874412Z"}, {"name": "execute", "started_at": "2025-10-15T03:53:19.875555Z", "completed_at": "2025-10-15T03:53:19.982697Z"}], "thread_id": "Thread-4 (worker)", "execution_time": 0.13742899894714355, "adapter_response": {"_message": "SELECT 1", "code": "SELECT", "rows_affected": 1}, "message": null, "failures": 0, "unique_id": "test.its_on_sale.not_null_price_events_ts_utc.dd91ee2019", "compiled": true, "compiled_code": "\n    \n    \n\n\n\nselect ts_utc\nfrom \"neondb\".\"public_marts\".\"price_events\"\nwhere ts_utc is null\n\n\n", "relation_name": null}, {"status": "pass", "timing": [{"name": "compile", "started_at": "2025-10-15T03:53:19.863812Z", "completed_at": "2025-10-15T03:53:19.877655Z"}, {"name": "execute", "started_at": "2025-10-15T03:53:19.879691Z", "completed_at": "2025-10-15T03:53:19.993464Z"}], "thread_id": "Thread-1 (worker)", "execution_time": 0.14916229248046875, "adapter_response": {"_message": "SELECT 1", "code": "SELECT", "rows_affected": 1}, "message": null, "failures": 0, "unique_id": "test.its_on_sale.not_null_stg_price_history_id.cb86572049", "compiled": true, "compiled_code": "\n    \n    \n\n\n\nselect id\nfrom \"neondb\".\"public_staging\".\"stg_price_history\"\nwhere id is null\n\n\n", "relation_name": null}, {"status": "pass", "timing": [{"name": "compile", "started_at": "2025-10-15T03:53:19.942123Z", "completed_at": "2025-10-15T03:53:19.948769Z"}, {"name": "execute", "started_at": "2025-10-15T03:53:19.949773Z", "completed_at": "2025-10-15T03:53:20.024824Z"}], "thread_id": "Thread-2 (worker)", "execution_time": 0.10253047943115234, "adapter_response": {"_message": "SELECT 1", "code": "SELECT", "rows_affected": 1}, "message": null, "failures": 0, "unique_id": "test.its_on_sale.not_null_stg_price_history_ts_utc.a6f1e7003a", "compiled": true, "compiled_code": "\n    \n    \n\n\n\nselect ts_utc\nfrom \"neondb\".\"public_staging\".\"stg_price_history\"\nwhere ts_utc is null\n\n\n", "relation_name": null}, {"status": "pass", "timing": [{"name": "compile", "started_at": "2025-10-15T03:53:19.967631Z", "completed_at": "2025-10-15T03:53:19.974235Z"}, {"name": "execute", "started_at": "2025-10-15T03:53:19.974235Z", "completed_at": "2025-10-15T03:53:20.077802Z"}], "thread_id": "Thread-3 (worker)", "execution_time": 0.1209709644317627, "adapter_response": {"_message": "SELECT 1", "code": "SELECT", "rows_affected": 1}, "message": null, "failures": 0, "unique_id": "test.its_on_sale.not_null_stg_product_product_id.5e35fa3f95", "compiled": true, "compiled_code": "\n    \n    \n\n\n\nselect product_id\nfrom \"neondb\".\"public_staging\".\"stg_product\"\nwhere product_id is null\n\n\n", "relation_name": null}, {"status": "pass", "timing": [{"name": "compile", "started_at": "2025-10-15T03:53:19.998113Z", "completed_at": "2025-10-15T03:53:20.003705Z"}, {"name": "execute", "started_at": "2025-10-15T03:53:20.004995Z", "completed_at": "2025-10-15T03:53:20.104828Z"}], "thread_id": "Thread-4 (worker)", "execution_time": 0.11880087852478027, "adapter_response": {"_message": "SELECT 1", "code": "SELECT", "rows_affected": 1}, "message": null, "failures": 0, "unique_id": "test.its_on_sale.not_null_stg_product_site.712843232d", "compiled": true, "compiled_code": "\n    \n    \n\n\n\nselect site\nfrom \"neondb\".\"public_staging\".\"stg_product\"\nwhere site is null\n\n\n", "relation_name": null}, {"status": "pass", "timing": [{"name": "compile", "started_at": "2025-10-15T03:53:20.018027Z", "completed_at": "2025-10-15T03:53:20.025832Z"}, {"name": "execute", "started_at": "2025-10-15T03:53:20.026896Z", "completed_at": "2025-10-15T03:53:20.118993Z"}], "thread_id": "Thread-1 (worker)", "execution_time": 0.11640739440917969, "adapter_response": {"_message": "SELECT 1", "code": "SELECT", "rows_affected": 1}, "message": null, "failures": 0, "unique_id": "test.its_on_sale.not_null_stg_product_url.2f8ccdc1e9", "compiled": true, "compiled_code": "\n    \n    \n\n\n\nselect url\nfrom \"neondb\".\"public_staging\".\"stg_product\"\nwhere url is null\n\n\n", "relation_name": null}, {"status": "pass", "timing": [{"name": "compile", "started_at": "2025-10-15T03:53:20.052024Z", "completed_at": "2025-10-15T03:53:20.069969Z"}, {"name": "execute", "started_at": "2025-10-15T03:53:20.069969Z", "completed_at": "2025-10-15T03:53:20.149882Z"}], "thread_id": "Thread-2 (worker)", "execution_time": 0.10946774482727051, "adapter_response": {"_message": "SELECT 1", "code": "SELECT", "rows_affected": 1}, "message": null, "failures": 0, "unique_id": "test.its_on_sale.relationships_fact_price_history_product_id__product_id__ref_stg_product_.42bbec0ccf", "compiled": true, "compiled_code": "\n    \n    \n\nwith child as (\n    select product_id as from_field\n    from \"neondb\".\"public_marts\".\"fact_price_history\"\n    where product_id is not null\n),\n\nparent as (\n    select product_id as to_field\n    from \"neondb\".\"public_staging\".\"stg_product\"\n)\n\nselect\n    from_field\n\nfrom child\nleft join parent\n    on child.from_field = parent.to_field\n\nwhere parent.to_field is null\n\n\n", "relation_name": null}, {"status": "pass", "timing": [{"name": "compile", "started_at": "2025-10-15T03:53:20.093570Z", "completed_at": "2025-10-15T03:53:20.104828Z"}, {"name": "execute", "started_at": "2025-10-15T03:53:20.108223Z", "completed_at": "2025-10-15T03:53:20.179036Z"}], "thread_id": "Thread-3 (worker)", "execution_time": 0.09474802017211914, "adapter_response": {"_message": "SELECT 1", "code": "SELECT", "rows_affected": 1}, "message": null, "failures": 0, "unique_id": "test.its_on_sale.relationships_stg_price_history_product_id__product_id__ref_stg_product_.055b801818", "compiled": true, "compiled_code": "\n    \n    \n\nwith child as (\n    select product_id as from_field\n    from \"neondb\".\"public_staging\".\"stg_price_history\"\n    where product_id is not null\n),\n\nparent as (\n    select product_id as to_field\n    from \"neondb\".\"public_staging\".\"stg_product\"\n)\n\nselect\n    from_field\n\nfrom child\nleft join parent\n    on child.from_field = parent.to_field\n\nwhere parent.to_field is null\n\n\n", "relation_name": null}, {"status": "pass", "timing": [{"name": "compile", "started_at": "2025-10-15T03:53:20.144445Z", "completed_at": "2025-10-15T03:53:20.150885Z"}, {"name": "execute", "started_at": "2025-10-15T03:53:20.151891Z", "completed_at": "2025-10-15T03:53:20.220537Z"}], "thread_id": "Thread-1 (worker)", "execution_time": 0.0863797664642334, "adapter_response": {"_message": "SELECT 1", "code": "SELECT", "rows_affected": 1}, "message": null, "failures": 0, "unique_id": "test.its_on_sale.unique_latest_price_per_product_product_id.dab72b4de6", "compiled": true, "compiled_code": "\n    \n    \n\nselect\n    product_id as unique_field,\n    count(*) as n_records\n\nfrom \"neondb\".\"public_marts\".\"latest_price_per_product\"\nwhere product_id is not null\ngroup by product_id\nhaving count(*) > 1\n\n\n", "relation_name": null}, {"status": "pass", "timing": [{"name": "compile", "started_at": "2025-10-15T03:53:20.122660Z", "completed_at": "2025-10-15T03:53:20.130971Z"}, {"name": "execute", "started_at": "2025-10-15T03:53:20.132096Z", "completed_at": "2025-10-15T03:53:20.224682Z"}], "thread_id": "Thread-4 (worker)", "execution_time": 0.1106424331665039, "adapter_response": {"_message": "SELECT 1", "code": "SELECT", "rows_affected": 1}, "message": null, "failures": 0, "unique_id": "test.its_on_sale.unique_fact_price_history_id.0da56e5a2d", "compiled": true, "compiled_code": "\n    \n    \n\nselect\n    id as unique_field,\n    count(*) as n_records\n\nfrom \"neondb\".\"public_marts\".\"fact_price_history\"\nwhere id is not null\ngroup by id\nhaving count(*) > 1\n\n\n", "relation_name": null}, {"status": "pass", "timing": [{"name": "compile", "started_at": "2025-10-15T03:53:20.162567Z", "completed_at": "2025-10-15T03:53:20.169328Z"}, {"name": "execute", "started_at": "2025-10-15T03:53:20.170461Z", "completed_at": "2025-10-15T03:53:20.251724Z"}], "thread_id": "Thread-2 (worker)", "execution_time": 0.09636473655700684, "adapter_response": {"_message": "SELECT 1", "code": "SELECT", "rows_affected": 1}, "message": null, "failures": 0, "unique_id": "test.its_on_sale.unique_stg_price_history_id.b6bbfe8a58", "compiled": true, "compiled_code": "\n    \n    \n\nselect\n    id as unique_field,\n    count(*) as n_records\n\nfrom \"neondb\".\"public_staging\".\"stg_price_history\"\nwhere id is not null\ngroup by id\nhaving count(*) > 1\n\n\n", "relation_name": null}, {"status": "pass", "timing": [{"name": "compile", "started_at": "2025-10-15T03:53:20.191879Z", "completed_at": "2025-10-15T03:53:20.197426Z"}, {"name": "execute", "started_at": "2025-10-15T03:53:20.197426Z", "completed_at": "2025-10-15T03:53:20.269630Z"}], "thread_id": "Thread-3 (worker)", "execution_time": 0.08591413497924805, "adapter_response": {"_message": "SELECT 1", "code": "SELECT", "rows_affected": 1}, "message": null, "failures": 0, "unique_id": "test.its_on_sale.unique_stg_product_product_id.fd1037e514", "compiled": true, "compiled_code": "\n    \n    \n\nselect\n    product_id as unique_field,\n    count(*) as n_records\n\nfrom \"neondb\".\"public_staging\".\"stg_product\"\nwhere product_id is not null\ngroup by product_id\nhaving count(*) > 1\n\n\n", "relation_name": null}, {"status": "fail", "timing": [{"name": "compile", "started_at": "2025-10-15T03:53:20.236914Z", "completed_at": "2025-10-15T03:53:20.244544Z"}, {"name": "execute", "started_at": "2025-10-15T03:53:20.245555Z", "completed_at": "2025-10-15T03:53:20.316983Z"}], "thread_id": "Thread-1 (worker)", "execution_time": 0.08980679512023926, "adapter_response": {"_message": "SELECT 1", "code": "SELECT", "rows_affected": 1}, "message": "Got 2 results, configured to fail if != 0", "failures": 2, "unique_id": "test.its_on_sale.unique_stg_product_url.35c93a6d66", "compiled": true, "compiled_code": "\n    \n    \n\nselect\n    url as unique_field,\n    count(*) as n_records\n\nfrom \"neondb\".\"public_staging\".\"stg_product\"\nwhere url is not null\ngroup by url\nhaving count(*) > 1\n\n\n", "relation_name": null}], "elapsed_time": 1.1390700340270996, "args": {"static_parser": true, "strict_mode": false, "indirect_selection": "eager", "use_colors_file": true, "select": [], "exclude": [], "use_colors": true, "log_file_max_bytes": 10485760, "introspect": true, "log_format": "default", "partial_parse": true, "print": true, "vars": {}, "invocation_command": "dbt test", "log_format_file": "debug", "partial_parse_file_diff": true, "profiles_dir": "C:\\Users\\meg\\Documents\\cam\\proj\\It's On Sale\\its-on-sale-tracker\\pipeline\\transform", "macro_debugging": false, "log_level": "info", "project_dir": "C:\\Users\\meg\\Documents\\cam\\proj\\It's On Sale\\its-on-sale-tracker\\pipeline\\transform\\its_on_sale", "require_explicit_package_overrides_for_builtin_materializations": true, "which": "test", "printer_width": 80, "warn_error_options": {"include": [], "exclude": []}, "send_anonymous_usage_stats": true, "favor_state": false, "source_freshness_run_project_hooks": false, "populate_cache": true, "show_resource_report": false, "log_level_file": "debug", "log_path": "C:\\Users\\meg\\Documents\\cam\\proj\\It's On Sale\\its-on-sale-tracker\\pipeline\\transform\\its_on_sale\\logs", "write_json": true, "quiet": false, "enable_legacy_logger": false, "cache_selected_only": false, "defer": false, "version_check": true, "require_resource_names_without_spaces": false}}